kineticstoolkit/VERSION
kineticstoolkit/__init__.py
kineticstoolkit/_repr.py
kineticstoolkit/classes.py
kineticstoolkit/config.py
kineticstoolkit/cycles.py
kineticstoolkit/decorators.py
kineticstoolkit/doc.py
kineticstoolkit/exceptions.py
kineticstoolkit/files.py
kineticstoolkit/filters.py
kineticstoolkit/geometry.py
kineticstoolkit/gui.py
kineticstoolkit/kinematics.py
kineticstoolkit/lab.py
kineticstoolkit/logo.png
kineticstoolkit/logo_hires.png
kineticstoolkit/player.py
kineticstoolkit/timeseries.py
kineticstoolkit/tools.py
kineticstoolkit/typing_.py
kineticstoolkit/dev/__init__.py
kineticstoolkit/dev/kinetics.py
kineticstoolkit/external/__init__.py
kineticstoolkit/external/icp.py
kineticstoolkit-0.17.0.dist-info/licenses/LICENSE.txt
kineticstoolkit-0.17.0.dist-info/licenses/NOTICE.txt
kineticstoolkit-0.17.0.dist-info/METADATA
kineticstoolkit-0.17.0.dist-info/WHEEL
kineticstoolkit-0.17.0.dist-info/top_level.txt
kineticstoolkit-0.17.0.dist-info/RECORD
